text_correction_benchmarks/__init__.py
text_correction_benchmarks/version.py
text_correction_benchmarks/baselines/__init__.py
text_correction_benchmarks/baselines/general.py
text_correction_benchmarks/baselines/sec.py
text_correction_benchmarks/baselines/seds.py
text_correction_benchmarks/baselines/sedw.py
text_correction_benchmarks/baselines/wsc.py
text_correction_benchmarks/cli/__init__.py
text_correction_benchmarks/cli/download.py
text_correction_benchmarks/cli/evaluate.py
text_correction_benchmarks-0.2.0.dist-info/LICENSE
text_correction_benchmarks-0.2.0.dist-info/METADATA
text_correction_benchmarks-0.2.0.dist-info/WHEEL
text_correction_benchmarks-0.2.0.dist-info/entry_points.txt
text_correction_benchmarks-0.2.0.dist-info/top_level.txt
text_correction_benchmarks-0.2.0.dist-info/RECORD
