Metadata-Version: 2.1
Name: text-correction-benchmarks
Version: 0.2.0
Summary: Benchmarks and evaluation tools for text correction tasks
Author-email: Sebastian Walter <swalter@cs.uni-freiburg.de>
License: Apache License
Project-URL: Github, https://github.com/ad-freiburg/text-correction-benchmarks
Keywords: nlp,text,correction,benchmark
Classifier: Programming Language :: Rust
Classifier: Programming Language :: Python :: 3
Classifier: Topic :: Scientific/Engineering :: Artificial Intelligence
Classifier: Topic :: Software Development :: Libraries
Classifier: Topic :: Text Processing
Classifier: Topic :: Utilities
Requires-Python: >=3.8
License-File: LICENSE
Requires-Dist: dtpu ==0.2.0
Requires-Dist: requests >=2.0.0
Requires-Dist: openai >=0.27.0
Provides-Extra: baselines
Requires-Dist: jamspell ; extra == 'baselines'
Requires-Dist: wordsegment ; extra == 'baselines'
